dabhounds/__init__.py
dabhounds/cli.py
dabhounds/core/__init__.py
dabhounds/core/auth.py
dabhounds/core/dab.py
dabhounds/core/library.py
dabhounds/core/musicbrainz.py
dabhounds/core/qobuz.py
dabhounds/core/report.py
dabhounds/core/spotify.py
dabhounds/core/spotify_auth.py
dabhounds/core/tui_report.py
dabhounds/core/youtube_parser_v3.py
dabhounds-2.1.0.dist-info/licenses/LICENSE
dabhounds-2.1.0.dist-info/METADATA
dabhounds-2.1.0.dist-info/WHEEL
dabhounds-2.1.0.dist-info/entry_points.txt
dabhounds-2.1.0.dist-info/top_level.txt
dabhounds-2.1.0.dist-info/RECORD
