Metadata-Version: 2.4
Name: dabhounds
Version: 2.1.0
Summary: Convert Spotify and YouTube playlists into DAB libraries
Author-email: sherlockholmesat221b <sherlockholmesat221b@proton.me>
License-Expression: MIT
Requires-Python: >=3.9
License-File: LICENSE
Requires-Dist: requests>=2.31.0
Requires-Dist: spotipy>=2.22.0
Requires-Dist: yt-dlp>=2025.07.06
Requires-Dist: musicbrainzngs>=0.7.1
Requires-Dist: rapidfuzz>=3.0.0
Dynamic: license-file
